setup.py
emcli/__init__.py
emcli/emcli.py
emcli/logger.py
emcli/storage.py
emcli.egg-info/PKG-INFO
emcli.egg-info/SOURCES.txt
emcli.egg-info/dependency_links.txt
emcli.egg-info/entry_points.txt
emcli.egg-info/requires.txt
emcli.egg-info/top_level.txt