Metadata-Version: 1.0
Name: emcli
Version: 0.2
Summary: A email client in terminal
Home-page: https://github.com/lalor/emcli
Author: Mingxing LAI
Author-email: me@mingxinglai.com
License: UNKNOWN
Platform: UNKNOWN
